README.txt
setup.py
print_helper/__init__.py
print_helper/inject_methods.py
print_helper.egg-info/PKG-INFO
print_helper.egg-info/SOURCES.txt
print_helper.egg-info/dependency_links.txt
print_helper.egg-info/top_level.txt